<?xml version="1.0" encoding="utf-8" standalone="yes"?>
<TangentWave fileType="PanelMap" fileVersion="3.0">
    <Panels>
        <Panel type="Element-Bt">
            <Mode id="0x0000000A"> <!-- Global -->
                <ControlBank id="Standard">
                    <Bank>
                        <Control type="Button" number="12"> <!-- Element-Bt Button A -->
                            <Mapping mode="Std">
                                <Key>0x80000001</Key> <!-- Select ALTernative Function -->
                            </Mapping>
                        </Control>
                        <Control type="Button" number="13"> <!-- Element-Bt Button B -->
                            <Mapping mode="Std">
                                <Key>0x80000009</Key> <!-- Next Mode -->
                            </Mapping>
                            <Mapping mode="Alt">
                                <Key>0x8000000A</Key> <!-- Previous Mode -->
                            </Mapping>
                        </Control>
                    </Bank>
                </ControlBank>
                <ControlBank id="Button">
                    <Bank>
                    </Bank>
                </ControlBank>
            </Mode>
            <Mode id="0x00010003"> <!-- FCP: Board -->
                <ControlBank id="Standard">
                    <Bank>
                        <Control type="Button" number="12"> <!-- Element-Bt Button A -->
                            <Mapping mode="Std">
                                <Key>0x80000001</Key> <!-- Select ALTernative Function -->
                            </Mapping>
                        </Control>
                        <Control type="Button" number="13"> <!-- Element-Bt Button B -->
                            <Mapping mode="Std">
                                <Key>0x80000009</Key> <!-- Next Mode -->
                            </Mapping>
                            <Mapping mode="Alt">
                                <Key>0x8000000A</Key> <!-- Previous Mode -->
                            </Mapping>
                        </Control>
                    </Bank>
                </ControlBank>
                <ControlBank id="Button">
                    <Bank>
                    </Bank>
                </ControlBank>
            </Mode>
            <Mode id="0x00010004"> <!-- FCP: Wheels -->
                <ControlBank id="Standard">
                    <Bank>
                        <Control type="Button" number="12"> <!-- Element-Bt Button A -->
                            <Mapping mode="Std">
                                <Key>0x80000001</Key> <!-- Select ALTernative Function -->
                            </Mapping>
                        </Control>
                        <Control type="Button" number="13"> <!-- Element-Bt Button B -->
                            <Mapping mode="Std">
                                <Key>0x80000009</Key> <!-- Next Mode -->
                            </Mapping>
                            <Mapping mode="Alt">
                                <Key>0x8000000A</Key> <!-- Previous Mode -->
                            </Mapping>
                        </Control>
                    </Bank>
                </ControlBank>
                <ControlBank id="Button">
                    <Bank>
                    </Bank>
                </ControlBank>
            </Mode>
        </Panel>
    </Panels>
</TangentWave>
